{
  "Ads":
  [
    {
      "select_main_ads": "APPLOVIN-D",
      "select_backup_ads":"",
      "main_ads_banner": "ca-app-pub-7492894468740102/6401155534",
      "main_ads_intertitial":"ca-app-pub-7492894468740102/9490902049",
      "native_for_admob":"ca-app-pub-7492894468740102/7825917843",
      "backup_ads_banner":"",
      "backup_ads_intertitial":"",
      "interval_intertitial": 6,
      "initialize_sdk":"",
      "initialize_sdk_backup_ads":"",
      "high_paying_keyword_1": "",
      "high_paying_keyword_2": "",
      "high_paying_keyword_3": "",
      "high_paying_keyword_4": "",
      "high_paying_keyword_5": "",
      "status_app": "0",
      "link_redirect": "https://"
    }
  ],

  "More":
  [
    {
      "id":1,
      "title":"MORE APP",
      "image":"file:///android_asset/play.png",
      "link":"https://play.google.com/store/apps/developer?id=Kimidroid"
    }
  ],
   "Skin":
  [

  ],
  "Addons":
  [
    {
      "id":1,
      "name_add":"Laser Guns",
      "add_url":"https://archive.org/download/add-on-kimidroid/addon/Laserguns.zip",
      "addB_url":"https://archive.org/download/add-on-kimidroid/addon/Laserguns-B.mcpack",
      "addR_url":"https://archive.org/download/add-on-kimidroid/addon/Laserguns-R.mcpack",
      "view_add":"https://plus62852.github.io/File/img-addon/lasergun.png",
      "des_add":"https://plus62852.github.io/File/addon.html"
    },
    {
      "id":2,
      "name_add":"Number Blocks",
      "add_url":"https://archive.org/download/add-on-kimidroid/addon/blocks.zip",
      "addB_url":"https://archive.org/download/add-on-kimidroid/addon/blocks-B.mcpack",
      "addR_url":"https://archive.org/download/add-on-kimidroid/addon/blocks-R.mcpack",
      "view_add":"https://plus62852.github.io/File/img-addon/numberblock.png",
      "des_add":"https://plus62852.github.io/File/addon.html"
    },
    {
      "id":3,
      "name_add":"The Imposter",
      "add_url":"https://archive.org/download/add-on-kimidroid/addon/Imposter.zip",
      "addB_url":"https://archive.org/download/add-on-kimidroid/addon/Imposter-B.mcpack",
      "addR_url":"https://archive.org/download/add-on-kimidroid/addon/Imposter-R.mcpack",
      "view_add":"https://plus62852.github.io/File/img-addon/imposter.png",
      "des_add":"https://plus62852.github.io/File/addon.html"
    },
    {
      "id":4,
      "name_add":"Uncrafting Table",
      "add_url":"https://archive.org/download/add-on-kimidroid/addon/Uncraftingtable.zip",
      "addB_url":"https://archive.org/download/add-on-kimidroid/addon/Uncraftingtable-B.mcpack",
      "addR_url":"https://archive.org/download/add-on-kimidroid/addon/Uncraftingtable-R.mcpack",
      "view_add":"https://plus62852.github.io/File/img-addon/uncrafting.png",
      "des_add":"https://plus62852.github.io/File/addon.html"
    },
    {
      "id":5,
      "name_add":"Furniture",
      "add_url":"https://archive.org/download/add-on-kimidroid/addon/furniture.zip",
      "addB_url":"https://archive.org/download/add-on-kimidroid/addon/furniture-B.mcpack",
      "addR_url":"https://archive.org/download/add-on-kimidroid/addon/furniture-R.mcpack",
      "view_add":"https://plus62852.github.io/File/img-addon/furniture.png",
      "des_add":"https://plus62852.github.io/File/addon.html"
    },
    {
      "id":6,
      "name_add":"Guns",
      "add_url":"https://archive.org/download/add-on-kimidroid/addon/guns.zip",
      "addB_url":"https://archive.org/download/add-on-kimidroid/addon/guns-B.mcpack",
      "addR_url":"https://archive.org/download/add-on-kimidroid/addon/guns-R.mcpack",
      "view_add":"https://plus62852.github.io/File/img-addon/gun.png",
      "des_add":"https://plus62852.github.io/File/addon.html"
    },
    {
      "id":7,
      "name_add":"Dynamite Projectile",
      "add_url":"https://archive.org/download/add-on-kimidroid/addon/dynamite.zip",
      "addB_url":"https://archive.org/download/add-on-kimidroid/addon/dynamite-B.mcpack",
      "addR_url":"https://archive.org/download/add-on-kimidroid/addon/dynamite-R.mcpack",
      "view_add":"https://plus62852.github.io/File/img-addon/dynamite.png",
      "des_add":"https://plus62852.github.io/File/addon.html"
    },
    {
      "id":8,
      "name_add":"Actual Guns",
      "add_url":"https://archive.org/download/actual-gun_202010/addon/ActualGun.zip",
      "addB_url":"https://archive.org/download/add-on-kimidroid/addon/ActualGunB.mcpack",
      "addR_url":"https://archive.org/download/add-on-kimidroid/addon/ActualGunR.mcpack",
      "view_add":"https://plus62852.github.io/File/img-addon/actualguns.png",
      "des_add":"https://plus62852.github.io/File/addon.html"
    }
  ],
  "Maps":
  [
    {
      "id":1,
      "name_map":"Bedrock Auto Chicken",
      "map_url":"https://archive.org/download/maps-kimidroid/maps/Bedrock.zip",
      "view_map":"https://plus62852.github.io/File/img-maps/badrok-min.png",
      "des_map":"https://plus62852.github.io/File/maps.html"
    },
    {
      "id":2,
      "name_map":"Among Us Map",
      "map_url":"https://archive.org/download/maps-kimidroid/maps/Among-us-Map.zip",
      "view_map":"https://plus62852.github.io/File/img-maps/among-min.png",
      "des_map":"https://plus62852.github.io/File/maps.html"
    },
    {
      "id":3,
      "name_map":"Cubical's Tower",
      "map_url":"https://archive.org/download/maps-kimidroid/maps/Cubicalstower.zip",
      "view_map":"https://plus62852.github.io/File/img-maps/Cubical-min.png",
      "des_map":"https://plus62852.github.io/File/maps.html"
    },
    {
      "id":4,
      "name_map":"Achievement World",
      "map_url":"https://archive.org/download/maps-kimidroid/maps/achievementworld.zip",
      "view_map":"https://plus62852.github.io/File/img-maps/Achievement-min.png",
      "des_map":"https://plus62852.github.io/File/maps.html"
    },
    {
      "id":5,
      "name_map":"HardCoreLine",
      "map_url":"https://archive.org/download/maps-kimidroid/maps/hardcoreline.zip",
      "view_map":"https://plus62852.github.io/File/img-maps/HardCoreLine-min.png",
      "des_map":"https://plus62852.github.io/File/maps.html"
    },
    {
      "id":6,
      "name_map":"Hello Neighbor",
      "map_url":"https://archive.org/download/maps-kimidroid/maps/hello-neighbour.zip",
      "view_map":"https://plus62852.github.io/File/img-maps/Neighbor-min.png",
      "des_map":"https://plus62852.github.io/File/maps.html"
    }
  ]
}
